setup.cfg
setup.py
catdb/__init__.py
catdb/db.py
catdb/main.py
catdb/mappings.conf
catdb/mysql.py
catdb/postgres.py
catdb.egg-info/PKG-INFO
catdb.egg-info/SOURCES.txt
catdb.egg-info/dependency_links.txt
catdb.egg-info/entry_points.txt
catdb.egg-info/requires.txt
catdb.egg-info/top_level.txt