Metadata-Version: 1.1
Name: catdb
Version: 0.0.2
Summary: Utility to copy data from various databases
Home-page: http://github.com/chimpler/catdb/
Author: Francois Dang Ngoc
Author-email: francois.dangngoc@gmail.com
License: Apache License 2.0
Keywords: catdb
Platform: UNKNOWN
Classifier: License :: OSI Approved :: Apache Software License
Classifier: Topic :: Software Development :: Libraries :: Python Modules
Classifier: Programming Language :: Python
Classifier: Programming Language :: Python :: 2
Classifier: Programming Language :: Python :: 2.6
Classifier: Programming Language :: Python :: 2.7
Classifier: Programming Language :: Python :: 3
Classifier: Programming Language :: Python :: 3.3
Classifier: Programming Language :: Python :: 3.4
